audinota/__init__.py
audinota/_version.py
audinota/api.py
audinota/cli.py
audinota/paths.py
audinota/transcribe.py
audinota/utils.py
audinota/vendor/__init__.py
audinota/vendor/pytest_cov_helper.py
audinota-0.1.1.dist-info/AUTHORS.rst
audinota-0.1.1.dist-info/LICENSE.txt
audinota-0.1.1.dist-info/METADATA
audinota-0.1.1.dist-info/WHEEL
audinota-0.1.1.dist-info/entry_points.txt
audinota-0.1.1.dist-info/RECORD
